earworm/__init__.py
earworm/feed.py
earworm/generate.py
earworm/metadata.py
earworm/static/bundle.js
earworm/static/main.css
earworm/template.html
earworm-0.4.0.dist-info/entry_points.txt
earworm-0.4.0.dist-info/LICENSE
earworm-0.4.0.dist-info/WHEEL
earworm-0.4.0.dist-info/METADATA
earworm-0.4.0.dist-info/RECORD
