Metadata-Version: 2.1
Name: earworm
Version: 0.4.0
Summary: Create a simple web page to listen to audio files in a directory
Home-page: https://punchagan.github.io/earworm/
Author: Puneeth Chaganti
Author-email: punchagan@muse-amuse.in
Requires-Python: >=3.7.13,<4.0.0
Classifier: Development Status :: 5 - Production/Stable
Classifier: Environment :: Console
Classifier: License :: OSI Approved :: GNU Affero General Public License v3
Classifier: Programming Language :: Python :: 3
Classifier: Programming Language :: Python :: 3.10
Classifier: Programming Language :: Python :: 3.6
Classifier: Programming Language :: Python :: 3.7
Classifier: Programming Language :: Python :: 3.8
Classifier: Programming Language :: Python :: 3.9
Classifier: Topic :: Multimedia :: Sound/Audio :: Players
Requires-Dist: Jinja2 (>=3.0.1,<4.0.0)
Requires-Dist: Pillow (>=8.2.0,<9.0.0)
Requires-Dist: PyYAML (>=5.4.1,<6.0.0)
Requires-Dist: dataclasses (>=0.8,<0.9); python_version >= "3.6" and python_version < "3.7"
Requires-Dist: feedgen (>=0.9.0,<0.10.0)
Requires-Dist: python-dateutil (>=2.8.1,<3.0.0)
Requires-Dist: requests (>=2.25.1,<3.0.0)
Requires-Dist: tinytag (>=1.5.0,<2.0.0)
Requires-Dist: webassets (>=2.0,<3.0)
Project-URL: Repository, https://github.com/punchagan/earworm/
